bionic/__init__.py
bionic/client.py
bionic/connection.py
bionic/errors.py
bionic/meta.py
bionic/models.py
bionic/server.py
bionic/sync.py
bionic/utils.py
bionicipc-2.1.0a0.dist-info/LICENSE
bionicipc-2.1.0a0.dist-info/METADATA
bionicipc-2.1.0a0.dist-info/WHEEL
bionicipc-2.1.0a0.dist-info/top_level.txt
bionicipc-2.1.0a0.dist-info/RECORD
